nagonbot/__init__.py
nagonbot/bot.py
nagonbot/bin/__init__.py
nagonbot/bin/data/SpeechPatterns.csv
nagonbot/bin/data/__init__.py
nagonbot/bin/data/kokoro.json
nagonbot/bin/data/model/__init__.py
nagonbot/bin/data/model/classes.pkl
nagonbot/bin/data/model/nagonmodel.h5
nagonbot/bin/data/model/words.pkl
nagonbot/bin/data/sound/__init__.py
nagonbot/bin/data/sound/temp/__init__.py
nagonbot/bin/tools/__init__.py
nagonbot/bin/tools/basic_sentence_functions.py
nagonbot/bin/tools/bgm.py
nagonbot/bin/tools/date_time.py
nagonbot/bin/tools/dictionary_bs4.py
nagonbot/bin/tools/flood_alert.py
nagonbot/bin/tools/function_selector.py
nagonbot/bin/tools/voice.py
nagonbot/bin/tools/weather.py
nagonbot/bin/tools/function_tools/__init__.py
nagonbot/bin/tools/function_tools/browser.py
nagonbot/bin/training/__init__.py
nagonbot/bin/training/csv_to_json.py
nagonbot/bin/training/json_reader.py
nagonbot/bin/training/model.py
nagonbot/bin/training/sql_to_csv.py
nagonbot/bin/training/sql_to_json.py
nagonbot/bin/training/training.py
nagonbot-1.0.0.dist-info/LICENSE.md
nagonbot-1.0.0.dist-info/LICENSE.txt
nagonbot-1.0.0.dist-info/METADATA
nagonbot-1.0.0.dist-info/WHEEL
nagonbot-1.0.0.dist-info/top_level.txt
nagonbot-1.0.0.dist-info/RECORD
