Metadata-Version: 2.1
Name: nagonbot
Version: 1.0.0
Summary: Japanese Chatbot
Home-page: https://github.com/FDSGAB/nagonbot
Author: Gabriel Fioravante Di Sciascio (FDSGAB)
Maintainer: Gabriel Fioravante Di Sciascio (FDSGAB)
License: LICENSE.txt
Keywords: python,chatbot,japanese,nagon,bot,artificial intelligence,virtual assistant
Classifier: Development Status :: 3 - Alpha
Classifier: Environment :: Console
Classifier: License :: OSI Approved :: MIT License
Classifier: Intended Audience :: End Users/Desktop
Classifier: Intended Audience :: Developers
Classifier: Programming Language :: Python :: 3
Classifier: Operating System :: Microsoft :: Windows
Requires-Python: <4,>=3.7
License-File: LICENSE.md
License-File: LICENSE.txt
Requires-Dist: keras
Requires-Dist: numpy
Requires-Dist: selenium
